Workbook

Sheet Cover Page
C13: Costco FP&A Operating Forecase & Variance Analysis
C15: Company: Costco Wholesale Corporation
C16: Ticker: COST
C17: Model Period: FY2023–FY2028
C18: Project Type: FP&A / Operating Forecast / Variance Analysis

Sheet Historical Financials
A1: Profit and Loss Statement
A2: [USD $ millions, except EPS]
A3: Line Item | B3: FY2021A | C3: FY2022A | D3: FY2023A | E3: FY2024A | F3: FY2025A
A4: Revenue stream 1 / Net Sales | B4: 192052 | C4: 222730 | D4: 237710 | E4: 249625 | F4: 269912
A5: Revenue stream 2 / Membership Fees | B5: 3877 | C5: 4224 | D5: 4580 | E5: 4828 | F5: 5323
A6: Returns, Refunds, Discounts | B6: - | C6: - | D6: - | E6: - | F6: -
A7: Total Net Revenue | B7: 195929 | C7: 226954 | D7: 242290 | E7: 254453 | F7: 275235
A9: Cost of Goods Sold / Merchandise Costs | B9: 170684 | C9: 199382 | D9: 212586 | E9: 222358 | F9: 239886
A10: Gross Profit incl. Membership Fees | B10: 25245 | C10: 27572 | D10: 29704 | E10: 32095 | F10: 35349
A12: Expenses
A13: SG&A | B13: 18537 | C13: 19779 | D13: 21590 | E13: 22810 | F13: 24966
A14: Total Expenses | B14: 18537 | C14: 19779 | D14: 21590 | E14: 22810 | F14: 24966
A15: Earnings Before Interest & Taxes | B15: 6708 | C15: 7793 | D15: 8114 | E15: 9285 | F15: 10383
A17: Interest Expense | B17: 171 | C17: 158 | D17: 160 | E17: 169 | F17: 154
A18: Interest Income & Other, Net | B18: 143 | C18: 205 | D18: 533 | E18: 624 | F18: 589
A19: Earnings Before Taxes | B19: 6680 | C19: 7840 | D19: 8487 | E19: 9740 | F19: 10818
A21: Income Taxes | B21: 1601 | C21: 1925 | D21: 2195 | E21: 2373 | F21: 2719
A22: Less: Net Income Attributable to Noncontrolling Interests | B22: 72 | C22: 71 | E22: - | F22: -
A23: Net Earnings Attributable to Costco | B23: 5007 | C23: 5844 | D23: 6292 | E23: 7367 | F23: 8099
A25: Diluted Shares | B25: 444.346 | C25: 444.757 | D25: 444.452 | E25: 444.759 | F25: 444.803
A26: Diluted EPS | B26: 11.27 | C26: 13.14 | D26: 14.16 | E26: 16.56 | F26: 18.21
A34: Costco Official Gross Margin Check
B35: FY2021A | C35: FY2022A | D35: FY2023A | E35: FY2024A | F35: FY2025A
A36: Net Sales | B36: 192052 | C36: 222730 | D36: 237710 | E36: 249625 | F36: 269912
A37: Less: Merchandise Costs | B37: 170684 | C37: 199382 | D37: 212586 | E37: 222358 | F37: 239886
A38: Official Merchandise Gross Margin | B38: 21368 | C38: 23348 | D38: 25124 | E38: 27267 | F38: 30026
A39: Official Gross Margin % | B39: 0.1113 | C39: 0.1048 | D39: 0.1057 | E39: 0.1092 | F39: 0.1112

Sheet Assumptions
A1: Costco Forecast Assumptions
A2: [USD $ millions, except EPS]
A3: Assumption | B3: FY2026E | C3: FY2027E | D3: FY2028E | E3: FY2029E
A4: Net Sales Growth | B4: 0.089597078 | C4: 0.089597078 | D4: 0.089597078 | E4: 0.089597078
A5: Membership Fee Growth | B5: 0.082614473 | C5: 0.082614473 | D5: 0.082614473 | E5: 0.082614473
A6: Merchandise Costs % of Net Sales | B6: 0.89154893 | C6: 0.89154893 | D6: 0.89154893 | E6: 0.89154893
A7: SG&A % of Total Revenue | B7: 0.090243986 | C7: 0.090243986 | D7: 0.090243986 | E7: 0.090243986
A8: Interest Expense | B8: 162.4 | C8: 162.4 | D8: 162.4 | E8: 162.4
A9: Interest Income & Other, Net | B9: 418.8 | C9: 418.8 | D9: 418.8 | E9: 418.8
A10: Tax Rate | B10: 0.24776242 | C10: 0.24776242 | D10: 0.24776242 | E10: 0.24776242
A11: Diluted Shares | B11: 444.6234 | C11: 444.6234 | D11: 444.6234 | E11: 444.6234

Sheet Operating Forecase
A1: Operating Forecast
A2: [USD $ millions, except EPS]
A3: Line Item | B3: FY2025A | C3: FY2026E | D3: FY2027E | E3: FY2028E | F3: FY2029E
A4: Revenue stream 1 / Net Sales | B4: ='Historical Financials'!F4 -> 269912 | C4: =B4*(1+Assumptions!B4) -> 294095.33 | D4: =C4*(1+Assumptions!C4) -> 320445.41 | E4: =D4*(1+Assumptions!D4) -> 349156.38 | F4: =E4*(1+Assumptions!E4) -> 380439.77
A5: Revenue stream 2 / Membership Fees | B5: ='Historical Financials'!F5 -> 5323 | C5: =B5*(1+Assumptions!B5) -> 5762.7568 | D5: =C5*(1+Assumptions!C5) -> 6238.844 | E5: =D5*(1+Assumptions!D5) -> 6754.2628 | F5: =E5*(1+Assumptions!E5) -> 7312.2626
A6: Returns, Refunds, Discounts | B6: 0 | C6: 0 | D6: 0 | E6: 0 | F6: 0
A7: Total Net Revenue | B7: ='Historical Financials'!F7 -> 275235 | C7: =SUM(C4:C6) -> 299858.08 | D7: =SUM(D4:D6) -> 326684.25 | E7: =SUM(E4:E6) -> 355910.64 | F7: =SUM(F4:F6) -> 387752.03
A9: Cost of Goods Sold / Merchandise Costs | B9: ='Historical Financials'!F9 -> 239886 | C9: =C4*Assumptions!B6 -> 262200.38 | D9: =D4*Assumptions!C6 -> 285692.76 | E9: =E4*Assumptions!D6 -> 311290 | F9: =F4*Assumptions!E6 -> 339180.67
A10: Gross Profit incl. Membership Fees | B10: ='Historical Financials'!F10 -> 35349 | C10: =C7-C9 -> 37657.708 | D10: =D7-D9 -> 40991.49 | E10: =E7-E9 -> 44620.644 | F10: =F7-F9 -> 48571.361
A12: Expenses
A13: SG&A | B13: =B14 -> 24966 | C13: =C7*Assumptions!B7 -> 27060.389 | D13: =D7*Assumptions!C7 -> 29481.289 | E13: =E7*Assumptions!D7 -> 32118.795 | F13: =F7*Assumptions!E7 -> 34992.289
A14: Total Expenses | B14: ='Historical Financials'!F14 -> 24966 | C14: =C13 -> 27060.389 | D14: =D13 -> 29481.289 | E14: =E13 -> 32118.795 | F14: =F13 -> 34992.289
A15: Earnings Before Interest & Taxes | B15: ='Historical Financials'!F15 -> 10383 | C15: =C10-C14 -> 10597.32 | D15: =D10-D14 -> 11510.201 | E15: =E10-E14 -> 12501.849 | F15: =F10-F14 -> 13579.072
A17: Interest Expense | B17: ='Historical Financials'!F17 -> 154 | C17: =Assumptions!B8 -> 162.4 | D17: =Assumptions!C8 -> 162.4 | E17: =Assumptions!D8 -> 162.4 | F17: =Assumptions!E8 -> 162.4
A18: Interest Income & Other, Net | B18: ='Historical Financials'!F18 -> 589 | C18: =Assumptions!B9 -> 418.8 | D18: =Assumptions!C9 -> 418.8 | E18: =Assumptions!D9 -> 418.8 | F18: =Assumptions!E9 -> 418.8
A19: Earnings Before Taxes | B19: ='Historical Financials'!F19 -> 10818 | C19: =C15-C17+C18 -> 10853.72 | D19: =D15-D17+D18 -> 11766.601 | E19: =E15-E17+E18 -> 12758.249 | F19: =F15-F17+F18 -> 13835.472
A21: Income Taxes | B21: ='Historical Financials'!F21 -> 2719 | C21: =C19*Assumptions!B10 -> 2689.1438 | D21: =D19*Assumptions!C10 -> 2915.3214 | E21: =E19*Assumptions!D10 -> 3161.0146 | F21: =F19*Assumptions!E10 -> 3427.91
A22: Less: Net Income Attributable to Noncontrolling Interests | B22: 0 | C22: 0 | D22: 0 | E22: 0 | F22: 0
A23: Net Earnings Attributable to Costco | B23: ='Historical Financials'!F23 -> 8099 | C23: =C19-C21-C22 -> 8164.5758 | D23: =D19-D21-D22 -> 8851.2794 | E23: =E19-E21-E22 -> 9597.2345 | F23: =F19-F21-F22 -> 10407.562
A25: Diluted Shares | B25: ='Historical Financials'!F25 -> 444.803 | C25: =Assumptions!B11 -> 444.6234 | D25: =Assumptions!C11 -> 444.6234 | E25: =Assumptions!D11 -> 444.6234 | F25: =Assumptions!E11 -> 444.6234
A26: Diluted EPS | B26: ='Historical Financials'!F26 -> 18.21 | C26: =C23/C25 -> 18.362902 | D26: =D23/D25 -> 19.907363 | E26: =E23/E25 -> 21.585086 | F26: =F23/F25 -> 23.40759

Sheet Scenario Analysis
A1: Setup Part 1: Scenario Assumptions
A2: [USD $ millions, except EPS]
A3: Scenario Assumptions | B3: Downside | C3: Base Case | D3: Upside
A4: Net Sales Growth | B4: 0.065 | C4: =Assumptions!B4 -> 0.089597078 | D4: 0.105
A5: Membership Fee Growth | B5: 0.065 | C5: =Assumptions!B5 -> 0.082614473 | D5: 0.095
A6: Merchandise Costs % of Net Sales | B6: 0.895 | C6: =Assumptions!B6 -> 0.89154893 | D6: 0.887
A7: SG&A % of Total Revenue | B7: 0.092 | C7: =Assumptions!B7 -> 0.090243986 | D7: 0.088
A8: Interest Expense | B8: =C8 -> 162.4 | C8: =Assumptions!B8 -> 162.4 | D8: =C8 -> 162.4
A9: Interest Income & Other, Net | B9: =C9 -> 418.8 | C9: =Assumptions!B9 -> 418.8 | D9: =C9 -> 418.8
A10: Tax Rate | B10: 0.25 | C10: =Assumptions!B10 -> 0.24776242 | D10: 0.245
A11: Diluted Shares | B11: =C11 -> 444.6234 | C11: =Assumptions!B11 -> 444.6234 | D11: =C11 -> 444.6234
A17: Setup Part 2: FY2029 Scenario Output
A18: [USD $ millions, except EPS]
A19: FY2029 Output | B19: Downside | C19: Base Case | D19: Upside
A20: Revenue stream 1 / Net Sales | B20: ='Operating Forecase'!B4*(1+'Scenario Analysis'!B4)^4 -> 347232.71 | C20: ='Operating Forecase'!B4*(1+'Scenario Analysis'!C4)^4 -> 380439.77 | D20: ='Operating Forecase'!C4*(1+'Scenario Analysis'!D4)^4 -> 438467.33
A21: Revenue stream 2 / Membership Fees | B21: ='Operating Forecase'!B5*(1+'Scenario Analysis'!B5)^4 -> 6847.8604 | C21: ='Operating Forecase'!C5*(1+'Scenario Analysis'!C5)^4 -> 7916.3614 | D21: ='Operating Forecase'!D5*(1+'Scenario Analysis'!D5)^4 -> 8969.3423
A22: Total Net Revenue | B22: =SUM(B20,B21) -> 354080.57 | C22: =SUM(C20,C21) -> 388356.13 | D22: =SUM(D20,D21) -> 447436.67
A23: Cost of Goods Sold / Merchandise Costs | B23: =B20*B6 -> 310773.27 | C23: =C20*C6 -> 339180.67 | D23: =D20*D6 -> 388920.52
A24: Gross Profit incl. Membership Fees | B24: =B22-B23 -> 43307.294 | C24: =C22-C23 -> 49175.46 | D24: =D22-D23 -> 58516.15
A25: SG&A | B25: =B22*B7 -> 32575.412 | C25: =C22*C7 -> 35046.805 | D25: =D22*D7 -> 39374.427
A26: Earnings Before Interest & Taxes | B26: =B24-B25 -> 10731.882 | C26: =C24-C25 -> 14128.654 | D26: =D24-D25 -> 19141.723
A27: Earnings Before Taxes | B27: =B26-B8+B9 -> 10988.282 | C27: =C26-C8+C9 -> 14385.054 | D27: =D26-D8+D9 -> 19398.123
A28: Income Taxes | B28: =B26*B10 -> 2682.9706 | C28: =C26*C10 -> 3500.5496 | D28: =D26*D10 -> 4689.7222
A29: Net Earnings Attributable to Costco | B29: =B27-B28 -> 8305.3118 | C29: =C27-C28 -> 10884.505 | D29: =D27-D28 -> 14708.401
A30: Diluted EPS | B30: =B29/B11 -> 18.67943 | C30: =C29/C11 -> 24.480279 | D30: =D29/D11 -> 33.080583

Sheet Sensitivity Analysis
A1: Sensitivity Analysis - FY2029 Diluted EPS Sensitivity
A2: [USD $ millions, except EPS]
A3: Merchandise Costs % of Net Sales
A4: ='Scenario Analysis'!C30 -> 24.480279 | B4: ='Scenario Analysis'!D6 -> 0.887 | C4: 0.89 | D4: ='Scenario Analysis'!C6 -> 0.89154893 | E4: 0.893 | F4: ='Scenario Analysis'!B6 -> 0.895
A5: Net Sales Growth | B5: - | C5: - | D5: - | E5: - | F5: -
A6: 0.065 | B6: 27.04 | C6: 25.16 | D6: 24.21 | E6: 23.27 | F6: 22.01
A7: 0.08 | B7: 27.25 | C7: 25.33 | D7: 24.38 | E7: 23.42 | F7: 22.14
A8: 0.0896 | B8: 27.38 | C8: 25.45 | D8: 24.48 | E8: 23.51 | F8: 22.23
A9: 0.1 | B9: 27.52 | C9: 25.57 | D9: 24.59 | E9: 23.62 | F9: 22.32
A10: 0.105 | B10: 27.58 | C10: 25.63 | D10: 24.65 | E10: 23.67 | F10: 22.36

Sheet Graphs Part 1
A1: Chart 1: FY2029 Total Net Revenue by Scenario | D1: Chart 2: FY2029 Diluted EPS by Scenario
A2: [USD $ millions, except EPS] | D2: [USD $ millions, except EPS]
A3: Scenario | B3: Total Net Revenue | D3: Scenario | H3: Diluted EPS
A4: Downside | B4: 354081 | D4: Downside | H4: 18.68
A5: Base Case | B5: 388356 | D5: Base Case | H5: 24.48
A6: Upside | B6: 447437 | D6: Upside | H6: 33.08

Sheet Graphs Part 2
A1: Chart 3: FY2029 EBIT and Net Earnings by Scenario | E1: Chart 4: FY2029 Margin Comparison by Scenario
A2: Scenario | B2: EBIT | C2: Net Earnings | E2: Scenario | F2: EBIT Margin | G2: Net Margin
A3: Downside | B3: 10732 | C3: 8305 | E3: Downside | F3: 0.0303 | G3: 0.0235
A4: Base Case | B4: 14129 | C4: 10885 | E4: Base Case | F4: 0.0364 | G4: 0.028
A5: Upside | B5: 19142 | C5: 14708 | E5: Upside | F5: 0.0428 | G5: 0.0329
